[
  {
    "name": "Warrior",
    "image": "/images/classtypes/warrior.webp",
    "abilities": {
      "strength": 15,
      "dexterity": 9,
      "constitution": 14,
      "intelligence": 8,
      "wisdom": 8,
      "charisma": 8
    }
  },
  {
    "name": "Cleric",
    "image": "/images/classtypes/cleric.webp",
    "abilities": {
      "strength": 13,
      "dexterity": 9,
      "constitution": 14,
      "intelligence": 8,
      "wisdom": 10,
      "charisma": 8
    }
  },
  {
    "name": "Ranger",
    "image": "/images/classtypes/ranger.webp",
    "abilities": {
      "strength": 13,
      "dexterity": 10,
      "constitution": 14,
      "intelligence": 8,
      "wisdom": 10,
      "charisma": 8
    }
  },
  {
    "name": "Rogue",
    "image": "/images/classtypes/rogue.webp",
    "abilities": {
      "strength": 13,
      "dexterity": 11,
      "constitution": 14,
      "intelligence": 8,
      "wisdom": 10,
      "charisma": 8
    }
  },
  {
    "name": "Wizard",
    "image": "/images/classtypes/wizard.webp",
    "abilities": {
      "strength": 8,
      "dexterity": 15,
      "constitution": 12,
      "intelligence": 13,
      "wisdom": 8,
      "charisma": 8
    }
  }
]
  